drf_info_endpoint/__init__.py
drf_info_endpoint/serializers.py
drf_info_endpoint/views.py
drf_info_endpoint-0.0.1.dist-info/LICENSE
drf_info_endpoint-0.0.1.dist-info/WHEEL
drf_info_endpoint-0.0.1.dist-info/METADATA
drf_info_endpoint-0.0.1.dist-info/RECORD
